instruction_test/__init__.py
instruction_test/instruction_test.py
instruction_test/test.py
instruction_test-0.1.0.dist-info/AUTHORS.rst
instruction_test-0.1.0.dist-info/LICENSE
instruction_test-0.1.0.dist-info/METADATA
instruction_test-0.1.0.dist-info/WHEEL
instruction_test-0.1.0.dist-info/top_level.txt
instruction_test-0.1.0.dist-info/RECORD
