Metadata-Version: 2.1
Name: instruction-test
Version: 0.1.0
Summary: This is a test package for following my Python package instructions 
Home-page: https://github.com/kalebswartz7/instruction_test
Author: Kaleb Robert Swartz 
Author-email: kalebswartz7@gmail.com
License: MIT license
Keywords: instruction_test
Platform: UNKNOWN
Classifier: Development Status :: 2 - Pre-Alpha
Classifier: Intended Audience :: Developers
Classifier: License :: OSI Approved :: MIT License
Classifier: Natural Language :: English
Classifier: Programming Language :: Python :: 2
Classifier: Programming Language :: Python :: 2.7
Classifier: Programming Language :: Python :: 3
Classifier: Programming Language :: Python :: 3.4
Classifier: Programming Language :: Python :: 3.5
Classifier: Programming Language :: Python :: 3.6
Classifier: Programming Language :: Python :: 3.7
